memintelli/__init__.py
memintelli/NN_layers/__init__.py
memintelli/NN_layers/activation.py
memintelli/NN_layers/convolution.py
memintelli/NN_layers/functions.py
memintelli/NN_layers/linear.py
memintelli/NN_layers/model_decorators.py
memintelli/NN_models/Bert.py
memintelli/NN_models/DeiT.py
memintelli/NN_models/ResNet.py
memintelli/NN_models/__init__.py
memintelli/NN_models/lenet5.py
memintelli/NN_models/vgg_cifar.py
memintelli/pimpy/__init__.py
memintelli/pimpy/memmat_tensor.py
memintelli/utils/__init__.py
memintelli/utils/data_formats.py
memintelli/utils/functions.py
memintelli-0.0.1.3.dist-info/METADATA
memintelli-0.0.1.3.dist-info/WHEEL
memintelli-0.0.1.3.dist-info/top_level.txt
memintelli-0.0.1.3.dist-info/RECORD
