Metadata-Version: 2.2
Name: memintelli
Version: 0.0.1.3
Summary: Memristive Intelligient Computing Simulator
Home-page: https://github.com/zzzzzzzzzzw/Memintelli
Author: Odysseia
Author-email: 1548384176@qq.com
License: MIT
Dynamic: author
Dynamic: author-email
Dynamic: description
Dynamic: description-content-type
Dynamic: home-page
Dynamic: license
Dynamic: summary
